LICENSE
MANIFEST.in
README.md
requirements.txt
setup.py
.github/ISSUE_TEMPLATE/bug_report.md
.github/ISSUE_TEMPLATE/feature_request.md
.pytest_cache/README.md
docs/requirements.txt
docs/build/html/_sources/authors.rst.txt
docs/build/html/_sources/changelog.rst.txt
docs/build/html/_sources/classifiers.rst.txt
docs/build/html/_sources/clustering.rst.txt
docs/build/html/_sources/index.rst.txt
docs/build/html/_sources/modules.rst.txt
docs/build/html/_sources/readme.rst.txt
docs/build/html/_sources/regressions.rst.txt
docs/build/html/_sources/vulpes.automl.rst.txt
docs/build/html/_sources/vulpes.rst.txt
docs/build/html/_sources/vulpes.tests.rst.txt
docs/build/html/_sources/vulpes.utils.rst.txt
docs/source/conf.py
vulpes/__init__.py
vulpes.egg-info/PKG-INFO
vulpes.egg-info/SOURCES.txt
vulpes.egg-info/dependency_links.txt
vulpes.egg-info/requires.txt
vulpes.egg-info/top_level.txt
vulpes/automl/__init__.py
vulpes/automl/classifiers.py
vulpes/automl/clustering.py
vulpes/automl/corevulpes.py
vulpes/automl/regressions.py
vulpes/tests/__init__.py
vulpes/tests/test_classifiers.py
vulpes/tests/test_clustering.py
vulpes/tests/test_others.py
vulpes/tests/test_regressions.py
vulpes/utils/__init__.py
vulpes/utils/utils.py