Metadata-Version: 2.1
Name: vulpes
Version: 0.2.0
Summary: Test many classification, regression models and clustering algorithms to see which one is most suitable for your dataset.
Home-page: https://vulpes.readthedocs.io/en/latest/
Download-URL: https://pypi.org/project/vulpes/
Author: Adrien Carrel
Author-email: a.carrel@hotmail.fr
Maintainer: Adrien Carrel
Maintainer-email: a.carrel@hotmail.fr
License: MIT
Project-URL: Bug Tracker, https://github.com/AdrienC21/vulpes/issues
Project-URL: Documentation, https://vulpes.readthedocs.io/en/latest/
Project-URL: Source Code, https://github.com/AdrienC21/vulpes
Keywords: vulpes,python,automl,scikit-learn,machine-learning,machine,learning,model,artificial,intelligence,clustering,dataset,classification,regression,hyperparameter-tuning
Platform: UNKNOWN
Classifier: Development Status :: 2 - Pre-Alpha
Classifier: Intended Audience :: Developers
Classifier: Intended Audience :: Science/Research
Classifier: Operating System :: Microsoft :: Windows
Classifier: Operating System :: MacOS :: MacOS X
Classifier: Operating System :: Unix
Classifier: License :: OSI Approved :: MIT License
Classifier: Programming Language :: Python :: 3
Classifier: Programming Language :: Python :: 3 :: Only
Classifier: Programming Language :: Python :: 3.7
Classifier: Topic :: Scientific/Engineering
Classifier: Topic :: Scientific/Engineering :: Artificial Intelligence
Classifier: Topic :: Scientific/Engineering :: Mathematics
Classifier: Topic :: Software Development
Classifier: Topic :: Software Development :: Libraries
Classifier: Topic :: Software Development :: Libraries :: Python Modules
Requires-Python: >=3.7
License-File: LICENSE
